kount/__init__.py
kount/client.py
kount/config.py
kount/inquiry.py
kount/request.py
kount/response.py
kount/settings.py
kount/version.py
kount/resources/__init__.py
kount/resources/correct_key_cryp.py
kount/util/__init__.py
kount/util/a85.py
kount/util/address.py
kount/util/cartitem.py
kount/util/khash.py
kount/util/payment.py
kount_ris_sdk-4.0.2.dist-info/LICENSE
kount_ris_sdk-4.0.2.dist-info/METADATA
kount_ris_sdk-4.0.2.dist-info/WHEEL
kount_ris_sdk-4.0.2.dist-info/top_level.txt
kount_ris_sdk-4.0.2.dist-info/RECORD
